siringa/__init__.py
siringa/analyzer.hy
siringa/annotation.hy
siringa/api.hy
siringa/container.hy
siringa/dependency.hy
siringa/errors.hy
siringa/inject.hy
siringa/invoke.hy
siringa/layer.hy
siringa/macros.hy
siringa/register.hy
siringa-0.1.3.dist-info/DESCRIPTION.rst
siringa-0.1.3.dist-info/METADATA
siringa-0.1.3.dist-info/RECORD
siringa-0.1.3.dist-info/WHEEL
siringa-0.1.3.dist-info/metadata.json
siringa-0.1.3.dist-info/top_level.txt
